{"en_cases_anti-occlusion.md":"D5EGhugz","en_cases_cooldown.md":"1p3esjGi","en_cases_custom-container.md":"r4TRg_xT","en_cases_custom-danmaku.md":"B0zwCweZ","en_cases_filter-keyword.md":"sOICyAKl","en_cases_fixed.md":"Caycd41r","en_cases_image.md":"C3FUmvER","en_cases_like.md":"CzE8_2aa","en_cases_loop.md":"CRX0Y6x1","en_cases_recommend.md":"yBS2Rgc-","en_cases_simplified-mode.md":"BkIAfnv3","en_cases_track-settings.md":"ym88BPMr","en_guide_create-plugin.md":"BSs3WW94","en_guide_getting-started.md":"C0TCwl4c","en_guide_typescript-interface.md":"CPd-XK15","en_index.md":"BbZpsJuk","en_reference_container-api.md":"ByDjSO77","en_reference_danmaku-api.md":"URkc5yfT","en_reference_danmaku-hooks.md":"CDLU8kyh","en_reference_danmaku-properties.md":"DlLphjmG","en_reference_manager-api.md":"DOOIyObO","en_reference_manager-configuration.md":"3Tzao0zW","en_reference_manager-hooks.md":"e26A3YqE","en_reference_manager-properties.md":"ZgQK6yQ1","en_reference_track-api.md":"zfcy6TV7","zh_cases_anti-occlusion.md":"BklD6Sab","zh_cases_cooldown.md":"CIdvNQRj","zh_cases_custom-container.md":"CL1o7SEQ","zh_cases_custom-danmaku.md":"BN1D7mPF","zh_cases_filter-keyword.md":"CuzmdNUm","zh_cases_fixed.md":"Db87VzBC","zh_cases_image.md":"CRgOcUu0","zh_cases_like.md":"CaJMgaJS","zh_cases_loop.md":"_2xoYeU2","zh_cases_recommend.md":"Dva235KA","zh_cases_simplified-mode.md":"BV4MX314","zh_cases_track-settings.md":"BxXYl9CO","zh_guide_create-plugin.md":"BFkJofxk","zh_guide_getting-started.md":"DSMK6cPG","zh_guide_typescript-interface.md":"DEN1RZrT","zh_index.md":"D0YNa9cq","zh_reference_container-api.md":"DLxrxZ2h","zh_reference_danmaku-api.md":"DLJL0FpW","zh_reference_danmaku-hooks.md":"Cb9hHHmz","zh_reference_danmaku-properties.md":"CR6RdaBV","zh_reference_manager-api.md":"BEahr_c4","zh_reference_manager-configuration.md":"rwyoy0_c","zh_reference_manager-hooks.md":"_4Ud6L_W","zh_reference_manager-properties.md":"iJbUrnOQ","zh_reference_track-api.md":"CBp51WpG"}
